dbfe/DistributionBasedFeatureExtractor.py
dbfe/MultiTypeDBFE.py
dbfe/__init__.py
dbfe/functions.py
dbfe/validation.py
dbfe-0.2.2.dist-info/LICENSE-BSD3.txt
dbfe-0.2.2.dist-info/LICENSE-CC-BY.txt
dbfe-0.2.2.dist-info/METADATA
dbfe-0.2.2.dist-info/WHEEL
dbfe-0.2.2.dist-info/top_level.txt
dbfe-0.2.2.dist-info/RECORD
