Metadata-Version: 2.1
Name: dbfe
Version: 0.2.2
Summary: Distribution-based feature extraction
Home-page: https://github.com/MNMdiagnostics/distribution_based_features
Author: Maciej Piernik
Author-email: maciej.piernik@mnm.bio
License: UNKNOWN
Platform: UNKNOWN
Classifier: Programming Language :: Python :: 3
Classifier: License :: OSI Approved :: BSD License
Classifier: Operating System :: OS Independent
Requires-Python: >=3.6
License-File: LICENSE-BSD3.txt
License-File: LICENSE-CC-BY.txt
